crc/__init__.py
crc/__main__.py
crc/_crc.py
crc/py.typed
crc-7.0.0.dist-info/entry_points.txt
crc-7.0.0.dist-info/LICENSE.txt
crc-7.0.0.dist-info/WHEEL
crc-7.0.0.dist-info/METADATA
crc-7.0.0.dist-info/RECORD
