Metadata-Version: 2.1
Name: crc
Version: 7.0.0
Summary: Library and CLI to calculate and verify all kinds of CRC checksums
Home-page: https://github.com/Nicoretti/crc
License: BSD-2-Clause
Keywords: CRC,CRC8,CRC16,CRC32,CRC64
Author: Nicola Coretti
Author-email: nico.coretti@gmail.com
Maintainer: Nicola Coretti
Maintainer-email: nico.coretti@gmail.com
Requires-Python: >=3.8,<4.0
Classifier: License :: OSI Approved :: BSD License
Classifier: Programming Language :: Python :: 3
Classifier: Programming Language :: Python :: 3.8
Classifier: Programming Language :: Python :: 3.9
Classifier: Programming Language :: Python :: 3.10
Classifier: Programming Language :: Python :: 3.11
Classifier: Programming Language :: Python :: 3
Classifier: Programming Language :: Python :: 3.10
Classifier: Programming Language :: Python :: 3.11
Classifier: Programming Language :: Python :: 3.12
Classifier: Programming Language :: Python :: 3.8
Classifier: Programming Language :: Python :: 3.9
Project-URL: Changelog, https://nicoretti.github.io/crc/changelog/unreleased/
Project-URL: Documentation, https://nicoretti.github.io/crc/
Project-URL: Homepage, https://nicoretti.github.io/crc/
Project-URL: Issues, https://github.com/Nicoretti/crc/issues
Project-URL: Repository, https://github.com/Nicoretti/crc
Project-URL: Source, https://github.com/Nicoretti/crc
